{
  "title": "Chivas Regal",
  "items": [
    {
      "text": "Pernod Ricard launches Chivas Regal Ultis",
      "createdAt": "2016-10-03T09:00:00",
      "starred": true,
      "upvotes": 124,
      "uri": "http://drinksint.com/news/fullstory.php/aid/6561/Pernod_launches_Chivas_Regal_Ultis.html",
      "image": "https://scotchwhisky.com/images/media/6425256b24d5a5368fc7f347768cd914.jpg",
      "comments": []
    },
    {
      "text": "Why has Chivas moved into blended malt?",
      "createdAt": "2016-10-03T09:00:00",
      "starred": false,
      "upvotes": 112,
      "uri": "https://scotchwhisky.com/magazine/in-depth/11303/why-has-chivas-moved-into-blended-malt/",
      "image": "https://scotchwhisky.com/images/media/0dffc02cce24fdc283b71739c7e48d8f.jpg",
      "comments": []
    },
    {
      "text": "New Brick Lane pop-up bar allows you to blend your own whisky",
      "createdAt": "2016-10-03T09:00:00",
      "starred": true,
      "upvotes": 109,
      "uri": "http://www.standard.co.uk/goingout/bars/new-brick-lane-popup-bar-allows-you-to-blend-your-own-whisky-a3363046.html",
      "image": "https://static.standard.co.uk/s3fs-public/styles/story_medium/public/thumbnails/image/2016/10/06/16/chivas-regal-whisky-pop-up-bar-opens-on-brick-lane.00-00-53-00.still002.jpg",
      "comments": []
    },
    {
      "text": "Pernod announces new Chivas blending team",
      "createdAt": "2016-09-13T09:00:00",
      "starred": false,
      "upvotes": 90,
      "uri": "http://drinksint.com/news/fullstory.php/aid/6529/Pernod_announces_new_Chivas_blending_team.html",
      "image": "http://www.tomswhiskyreviews.com/images/chivas_blenders_530.jpg",
      "comments": []
    },
    {
      "text": "How to make whisky: The new classes that let you create your own blend",
      "createdAt": "2016-10-03T09:00:00",
      "starred": false,
      "upvotes": 87,
      "uri": "http://www.independent.co.uk/life-style/food-and-drink/how-to-make-whisky-blend-chivas-regal-shoreditch-truman-brewery-a7349811.html",
      "image": "https://static.independent.co.uk/s3fs-public/styles/story_large/public/thumbnails/image/2016/10/07/10/chivastheblend-05oct16-1050-db.jpg",
      "comments": []
    },
    {
      "text": "Chivas Regal opens applications for $1m The Venture competition",
      "createdAt": "2016-10-03T09:00:00",
      "starred": false,
      "upvotes": 76,
      "uri": "http://disrupt-africa.com/2016/09/chivas-regal-opens-applications-for-1m-the-venture-competition/",
      "image": "http://disrupt-africa.com/wp-content/uploads/2015/07/lumkani-702x336.jpeg",
      "comments": []
    },
    {
      "text": "Chivas Regal devises whisky blending activation",
      "createdAt": "2016-10-03T09:00:00",
      "starred": false,
      "upvotes": 67,
      "uri": "http://www.eventmagazine.co.uk/chivas-regal-devises-whisky-blending-activation/brands/article/1409369",
      "image": "http://cached.imagescaler.hbpl.co.uk/resize/scaleWidth/620/offlinehbpl.hbpl.co.uk/news/OVE/chivas-20160919102036322.jpg",
      "comments": []
     },
     {
      "text": "Tumi Molekane is the national ambassador for Chivas Regal",
      "createdAt": "2016-10-03T09:00:00",
      "starred": false,
      "upvotes": 56,
      "uri": "https://www.zalebs.com/whats-hot/tumi-molekane-national-ambassador-chivas-regal/",
      "image": "https://zalebs-cdn.kagiso.io/images/Stogie_T_Chivas_Regal.original.jpg",
      "comments": []
    },
    {
      "text": "Chivas unveils limited edition gift tin",
      "createdAt": "2016-10-03T09:00:00",
      "starred": false,
      "upvotes": 44,
      "uri": "https://medium.com/@rynmcmns/what-will-you-do-in-a-car-when-it-drives-itself-efdac3b6e5a5#.czscuq9w3",
      "image": "http://www.thespiritsbusiness.com/content/http://www.thespiritsbusiness.com/media/2016/09/Chivas-Regal-Pininfarina-WEB.jpg",
      "comments": []
    }
  ]
}
